ai_kit_auth/__init__.py
ai_kit_auth/admin.py
ai_kit_auth/apps.py
ai_kit_auth/models.py
ai_kit_auth/serializers.py
ai_kit_auth/services.py
ai_kit_auth/settings.py
ai_kit_auth/signals.py
ai_kit_auth/urls.py
ai_kit_auth/views.py
ai_kit_auth/migrations/__init__.py
ai_kit_auth/templates/ai_kit_auth/body_base.html
ai_kit_auth/templates/ai_kit_auth/reset_password_body.html
ai_kit_auth/templates/ai_kit_auth/reset_password_body.txt
ai_kit_auth/templates/ai_kit_auth/reset_password_title.txt
ai_kit_auth/templates/ai_kit_auth/set_password_body.html
ai_kit_auth/templates/ai_kit_auth/set_password_body.txt
ai_kit_auth/templates/ai_kit_auth/set_password_title.txt
ai_kit_auth/templates/ai_kit_auth/user_created_body.html
ai_kit_auth/templates/ai_kit_auth/user_created_body.txt
ai_kit_auth/templates/ai_kit_auth/user_created_title.txt
ai_kit_auth/tests/__init__.py
ai_kit_auth/tests/serializers.py
ai_kit_auth/tests/settings.py
ai_kit_auth/tests/test_admin.py
ai_kit_auth/tests/test_api.py
ai_kit_auth/tests/test_services.py
ai_kit_auth/tests/test_settings.py
django_ai_kit_auth-2.0.0.dist-info/METADATA
django_ai_kit_auth-2.0.0.dist-info/WHEEL
django_ai_kit_auth-2.0.0.dist-info/top_level.txt
django_ai_kit_auth-2.0.0.dist-info/RECORD
